abics/.gitignore
abics/__init__.py
abics/applications/__init__.py
abics/applications/latgas_abinitio_interface/__init__.py
abics/applications/latgas_abinitio_interface/aenet.py
abics/applications/latgas_abinitio_interface/aenet_pylammps.py
abics/applications/latgas_abinitio_interface/aenet_trainer.py
abics/applications/latgas_abinitio_interface/base_solver.py
abics/applications/latgas_abinitio_interface/base_trainer.py
abics/applications/latgas_abinitio_interface/default_observer.py
abics/applications/latgas_abinitio_interface/defect.py
abics/applications/latgas_abinitio_interface/map2perflat.py
abics/applications/latgas_abinitio_interface/mlip_3.py
abics/applications/latgas_abinitio_interface/mlip_3_trainer.py
abics/applications/latgas_abinitio_interface/model_setup.py
abics/applications/latgas_abinitio_interface/naive_matcher.py
abics/applications/latgas_abinitio_interface/nequip.py
abics/applications/latgas_abinitio_interface/nequip_trainer.py
abics/applications/latgas_abinitio_interface/openmx.py
abics/applications/latgas_abinitio_interface/params.py
abics/applications/latgas_abinitio_interface/qe.py
abics/applications/latgas_abinitio_interface/run_base_mpi.py
abics/applications/latgas_abinitio_interface/user_function_solver.py
abics/applications/latgas_abinitio_interface/util.py
abics/applications/latgas_abinitio_interface/vasp.py
abics/applications/lattice_model/__init__.py
abics/applications/lattice_model/potts.py
abics/exception.py
abics/loggers/README.txt
abics/loggers/__init__.py
abics/loggers/loggers.py
abics/mc.py
abics/mc_mpi.py
abics/mlref.py
abics/model.py
abics/observer.py
abics/replica_params.py
abics/sampling/__init__.py
abics/sampling/mc.py
abics/sampling/mc_mpi.py
abics/sampling/pamc.py
abics/sampling/resampling.py
abics/sampling/rxmc.py
abics/sampling/simple_parallel.py
abics/scripts/__init__.py
abics/scripts/abicsRXsepT.py
abics/scripts/activelearn.py
abics/scripts/input_template.toml
abics/scripts/main.py
abics/scripts/main_dft_latgas.py
abics-2.2.1.dist-info/COPYING
abics-2.2.1.dist-info/METADATA
abics-2.2.1.dist-info/WHEEL
abics-2.2.1.dist-info/entry_points.txt
abics-2.2.1.dist-info/RECORD
