Metadata-Version: 2.1
Name: abics
Version: 2.2.1
Summary: ab-Initio Configuration Sampling tool kit
Home-page: https://github.com/issp-center-dev/abICS
License: GPL-3.0-or-later
Author: abICS developers
Author-email: abics-dev@issp.u-tokyo.ac.jp
Requires-Python: >=3.9,<4.0
Classifier: License :: OSI Approved :: GNU General Public License v3 or later (GPLv3+)
Classifier: Programming Language :: Python :: 3
Classifier: Programming Language :: Python :: 3.9
Classifier: Programming Language :: Python :: 3.10
Classifier: Programming Language :: Python :: 3.11
Classifier: Programming Language :: Python :: 3.12
Classifier: Programming Language :: Python :: 3.13
Provides-Extra: nequip
Requires-Dist: mpi4py (>=3,<4)
Requires-Dist: nequip (>=0.5.6) ; extra == "nequip"
Requires-Dist: numpy (>=1.20,<2.0)
Requires-Dist: pymatgen (>=2022.1.20)
Requires-Dist: qe_tools (>=1.1,<2.0)
Requires-Dist: scipy (>=1,<2)
Requires-Dist: toml (>=0.10)
Project-URL: Repository, https://github.com/issp-center-dev/abICS
